at_external_fmp/__init__.py
at_external_fmp/_client.py
at_external_fmp/analyst.py
at_external_fmp/calendar.py
at_external_fmp/chart.py
at_external_fmp/commodity.py
at_external_fmp/company.py
at_external_fmp/crypto.py
at_external_fmp/directory.py
at_external_fmp/economics.py
at_external_fmp/esg.py
at_external_fmp/etf_and_mutual_funds.py
at_external_fmp/forex.py
at_external_fmp/index.py
at_external_fmp/market_hours.py
at_external_fmp/market_performance.py
at_external_fmp/news.py
at_external_fmp/quote.py
at_external_fmp/search.py
at_external_fmp/statements.py
at_external_fmp/schema/analyst.py
at_external_fmp/schema/calendar.py
at_external_fmp/schema/chart.py
at_external_fmp/schema/commodity.py
at_external_fmp/schema/company.py
at_external_fmp/schema/crypto.py
at_external_fmp/schema/directory.py
at_external_fmp/schema/economics.py
at_external_fmp/schema/esg.py
at_external_fmp/schema/etf_and_mutual_funds.py
at_external_fmp/schema/forex.py
at_external_fmp/schema/index.py
at_external_fmp/schema/market_hours.py
at_external_fmp/schema/market_performance.py
at_external_fmp/schema/news.py
at_external_fmp/schema/quote.py
at_external_fmp/schema/search.py
at_external_fmp/schema/statements.py
at_external_fmp-1.0.1.dist-info/METADATA
at_external_fmp-1.0.1.dist-info/WHEEL
at_external_fmp-1.0.1.dist-info/top_level.txt
at_external_fmp-1.0.1.dist-info/RECORD
