Metadata-Version: 2.2
Name: at-external-fmp
Version: 1.0.1
Summary: Provides an API client for retrieving financial data from the Financial Modeling Prep API, organized into structured modules for various financial metrics.
Author: Rui Chen
Project-URL: Homepage, https://github.com/apex-trader/at-external-fmp
Project-URL: Bug Tracker, https://github.com/apex-trader/at-external-fmp/issues
Requires-Python: >=3.11
